template_py/__init__.py
template_py/template_py.py
tpl.py-1.4.3.dist-info/LICENSE
tpl.py-1.4.3.dist-info/METADATA
tpl.py-1.4.3.dist-info/WHEEL
tpl.py-1.4.3.dist-info/entry_points.txt
tpl.py-1.4.3.dist-info/top_level.txt
tpl.py-1.4.3.dist-info/RECORD
