Metadata-Version: 2.1
Name: tpl.py
Version: 1.4.3
License-File: LICENSE
Requires-Dist: jinja2
Requires-Dist: cryptography
